faux/__init__.py
faux/__main__.py
faux/client.py
faux/server.py
faux/utils.py
faux-0.0.7.dist-info/DESCRIPTION.rst
faux-0.0.7.dist-info/METADATA
faux-0.0.7.dist-info/RECORD
faux-0.0.7.dist-info/WHEEL
faux-0.0.7.dist-info/entry_points.txt
faux-0.0.7.dist-info/metadata.json
faux-0.0.7.dist-info/top_level.txt
