Metadata-Version: 2.0
Name: faux
Version: 0.0.7
Summary: Quick and easy server mocking.
Home-page: https://github.com/bprinty/faux
Author: bprinty
Author-email: bprinty@gmail.com
License: UNKNOWN
Keywords: faux
Platform: UNKNOWN
Classifier: Development Status :: 4 - Beta
Classifier: Intended Audience :: Developers
Classifier: License :: OSI Approved :: BSD License
Classifier: Natural Language :: English
Classifier: Programming Language :: Python :: 2
Classifier: Programming Language :: Python :: 2.6
Classifier: Programming Language :: Python :: 2.7
Classifier: Programming Language :: Python :: 3
Classifier: Programming Language :: Python :: 3.3
Classifier: Programming Language :: Python :: 3.4
Requires-Dist: Flask (>=0.10.1)
Requires-Dist: faker (>=1.0.1)
